ntripstreams/__init__.py
ntripstreams/__main__.py
ntripstreams/__version__.py
ntripstreams/crc.py
ntripstreams/ntripstreams.py
ntripstreams/rtcm3.py
ntripstreams-0.2.1.dist-info/LICENSE
ntripstreams-0.2.1.dist-info/METADATA
ntripstreams-0.2.1.dist-info/WHEEL
ntripstreams-0.2.1.dist-info/top_level.txt
ntripstreams-0.2.1.dist-info/RECORD
