Metadata-Version: 2.1
Name: ntripstreams
Version: 0.2.1
Summary: Library for Ntrip communication
Home-page: https://github.com/stenseng/ntripstreams
Author: Lars Stenseng
Author-email: lars@stenseng.net
License: MIT
Platform: UNKNOWN
Classifier: License :: OSI Approved :: MIT License
Classifier: Development Status :: 3 - Alpha
Classifier: Programming Language :: Python
Classifier: Programming Language :: Python :: 3
Classifier: Programming Language :: Python :: 3.7
Classifier: Programming Language :: Python :: 3.8
Classifier: Programming Language :: Python :: 3.9
Classifier: Programming Language :: Python :: Implementation :: CPython
Classifier: Topic :: Internet
Requires-Python: >=3.7.0
License-File: LICENSE
Requires-Dist: bitstring
